dart_bridge.cpython-312-x86_64-linux-gnu.so
dart_api/dart_api.h
dart_api/dart_api_dl.c
dart_api/dart_api_dl.h
dart_api/dart_native_api.h
dart_api/dart_tools_api.h
dart_api/dart_version.h
dart_api/internal/dart_api_dl_impl.h
dart_bridge-0.4.2.dist-info/METADATA
dart_bridge-0.4.2.dist-info/WHEEL
dart_bridge-0.4.2.dist-info/top_level.txt
dart_bridge-0.4.2.dist-info/RECORD
dart_bridge-0.4.2.dist-info/licenses/LICENSE
