Metadata-Version: 2.4
Name: dart-bridge
Version: 0.4.2
Summary: A Python C extension for interacting with the Dart SDK from Python
Author-email: Flet Team <hello@flet.dev>
Project-URL: Homepage, https://github.com/flet-dev/dart-bridge
Project-URL: Issues, https://github.com/flet-dev/dart-bridge/issues
Keywords: dart,ffi,bridge,cython
Classifier: Programming Language :: Python :: 3
Classifier: Programming Language :: Python :: 3.10
Classifier: Programming Language :: Python :: 3.11
Classifier: Programming Language :: Python :: 3.12
Classifier: Programming Language :: C
Classifier: Programming Language :: Cython
Classifier: Operating System :: OS Independent
Classifier: Topic :: Software Development :: Libraries :: Python Modules
Requires-Python: >=3.10
License-File: LICENSE
Dynamic: license-file
